{
  "rewards": [
    {
      "id": 1,
      "name": "Amazon Gift Card",
      "value": 1000,
      "description": "Gift card valid for purchases on Amazon",
      "expirationDate": "2024-12-31"
    },
    {
      "id": 2,
      "name": "Starbucks Voucher",
      "value": 20,
      "description": "Voucher for Starbucks coffee and beverages",
      "expiration_date": "2024-10-15"
    },
    {
      "id": 3,
      "name": "Netflix Subscription",
      "value": 15,
      "description": "Subscription to Netflix streaming service",
      "expiration_date": "2025-01-15"
    }
  ]
}
